{
  "query": "Hacettepe araştırma merkezleri nelerdir",
  "answer": "Hacettepe Üniversitesi'nde Türkçe ve Yabancı Dil Öğretimi Uygulama ve Araştırma Merkezinin adı geçmektedir.\n\n**Kaynaklar:**\nYeniYonetmelik.pdf, sosyal_destek_yonerge_280324.pdf, Hacettepe Üniversitesi Program Dışı Öğrenmelerin Tanınması Yönergesi.pdf\n\n**Kullanılan Chunklar:**\n\n[1] (YeniYonetmelik.pdf):\nMADDE 4 – (1) Bu Yönetmelikte geçen; a) Birim Başkanı: Merkezin Birim Başkanını, b) Merkez (HÜTÖMER): Hacettepe Üniversitesi Türkçe ve Yabancı Dil Öğretimi Uygulama ve Araştırma Merkezini, c) Müdür: Merkezin Müdürünü, ç) Rektör: Hacettepe Üniversitesi Rektörünü, d) Üniversite: Hacettepe Üniversitesini, e) Yönetim Kurulu: Merkezin Yönetim Kurulunu, ifade eder. İKİNCİ BÖLÜM Merkezin Amaçları ve Faaliyet Alanları Merkezin amacı ve faaliyet alanları\n\n[2] (YeniYonetmelik.pdf):\nMADDE 1 – (1) Bu Yönetmeliğin amacı; Hacettepe Üniversitesine bağlı olarak kurulan Hacettepe Üniversitesi Türkçe ve Yabancı Dil Öğretimi Uygulama ve Araştırma Merkezinin amaçlarına, faaliyet alanlarına, yönetim organlarına ve bu organların görevlerine ilişkin usul ve esasları düzenlemektir. Kapsam\n\n[3] (Hacettepe Üniversitesi Program Dışı Öğrenmelerin Tanınması Yönergesi.pdf):\nMADDE 4 – (1) Bu Yönerge’de geçen; a) Birim: Başvurulan programın bağlı olduğu fakülte, enstitü, yüksekokul, konservatuvar ve meslek yüksekokulunu, b) Dekan: Hacettepe Üniversitesine bağlı fakülte dekanlarını, c) Komisyon: Birimlerde program dışı öğrenmelerin tanınmasına yönelik yapılan başvuruları değerlendiren program dışı öğrenmeleri değerlendirme komisyonunu, ç) Müdür: Hacettepe Üniversitesine bağlı enstitü, yüksekokul, konservatuvar ve meslek yüksekokulu müdürlerini, d) Program dışı öğrenme: Öğrencinin devam ettiği program süresi içinde ancak program gereği aldığı eğitim dışında, iş yaşamı ve günlük yaşam içerisinde elde ettiği yayınlar, projeler, araştırma ve destekler, yurtiçi ya da dışında yapılan gönüllü çalışmalar, mikro yeterlilik ya da yüz yüze/çevrim içi sertifika programlarından alınan ders/ kurs/ eğitimler sonucunda elde edilen öğrenmeleri, e) Program dışı öğrenme transkripti: Kabul edilmesine karar verilerek onaylanan program dışı elde edilen öğrenmelerin işlendiği belgeyi, f) Rektör: Hacettepe Üniversitesi Rektörünü, g) Senato: Hacettepe Üniversitesi Senatosunu, ğ) Yönetim Kurulu: İlgili birim Yönetim Kurulunu ifade eder. Komisyonun oluşumu, görevleri ve çalışma esasları\n\n[4] (Hacettepe Üniversitesi Program Dışı Öğrenmelerin Tanınması Yönergesi.pdf):\nMADDE 2- (1) Bu Yönerge, Hacettepe Üniversitesi ön lisans, lisans ve lisansüstü programlarına kayıt yaptırmış öğrencilerin; program dışı öğrenmeler sonucunda kazanılan bilgi, beceri ve yetkinliklerinin, üniversitenin ilgili kurullarınca kabul edilen kurumlardan ya da nitelikli mikro yeterlik sağlayıcılarından elde edilen sertifika, belge (rozet), yayınlar, projeler, araştırma ve destekler; belgelendirilebilen (yurtiçi/yurtdışı) gönüllü çalışmalar, iş yerinde mesleki, staj, klinik çalışma veya saha çalışması deneyimlerinin tanınması, değerlendirilmesi işlemlerine ilişkin esasları kapsar. Dayanak\n\n[5] (sosyal_destek_yonerge_280324.pdf):\nMADDE 3- (1) Bu Yönergede adı geçen; a) Birim: Hacettepe Üniversitesi bünyesinde kurulan fakülteler, yüksekokullar, meslek yüksekokulları ve Ankara Devlet Konservatuarını, b) Birim Destek Komisyonu: Hacettepe Üniversitesi birimlerinde oluşturulan komisyonu, c) BİDB: Hacettepe Üniversitesi Bilgi İşlem Daire Başkanlığını, ç) GANO: Genel akademik not ortalamasını, d) KYK: Yükseköğrenim Kredi ve Yurtlar Kurumunu, e) Komisyon: Hacettepe Üniversitesi Öğrenci Sosyal Destek Komisyonunu, f) ÖİDB: Hacettepe Üniversitesi Öğrenci İşleri Daire Başkanlığını, g) ÖSYM: Öğrenci Seçme ve Yerleştirme Merkezini, ğ) Öğrenci: Hacettepe Üniversitesi lisans, ön lisans ve konservatuvar öğrencilerini h) Rektör: Hacettepe Üniversitesi Rektörünü, 2 / 6 ı) Rektör Yardımcısı: Hacettepe Üniversitesi Rektör Yardımcısını, i) Senato: Hacettepe Üniversitesi Senatosunu, j) SKSDB: Hacettepe Üniversitesi Sağlık, Kültür ve Spor Daire Başkanlığını, k) SGDB: Hacettepe Üniversitesi Strateji Geliştirme Daire Başkanlığını, l) Üniversite: Hacettepe Üniversitesini, m) Yönetim Kurulu: Hacettepe Üniversitesi Yönetim Kurulunu ifade eder. İKİNCİ BÖLÜM Destek Türleri ve Verilmesine İlişkin Esaslar Destek türleri\n\n[6] (YeniYonetmelik.pdf):\nMADDE 2 – (1) Bu Yönetmelik, Hacettepe Üniversitesi Türkçe ve Yabancı Dil Öğretimi Uygulama ve Araştırma Merkezinin amaçlarına, faaliyet alanlarına, yönetim organlarına, yönetim organlarının görevlerine ilişkin hükümleri kapsar. Dayanak\n",
  "timestamp": 1765484322.9279172,
  "metadata": {
    "sources": "YeniYonetmelik.pdf, sosyal_destek_yonerge_280324.pdf, Hacettepe Üniversitesi Program Dışı Öğrenmelerin Tanınması Yönergesi.pdf",
    "num_chunks": 6
  }
}